{
	"configurations" : 
	[
		{
			"directories" : 
			[
				{
					"build" : ".",
					"jsonFile" : "directory-.-Debug-f5ebdc15457944623624.json",
					"minimumCMakeVersion" : 
					{
						"string" : "3.20"
					},
					"projectIndex" : 0,
					"source" : ".",
					"targetIndexes" : 
					[
						0,
						1,
						2,
						3
					]
				}
			],
			"name" : "Debug",
			"projects" : 
			[
				{
					"directoryIndexes" : 
					[
						0
					],
					"name" : "subgraph_search",
					"targetIndexes" : 
					[
						0,
						1,
						2,
						3
					]
				}
			],
			"targets" : 
			[
				{
					"directoryIndex" : 0,
					"id" : "memcheck::@6890427a1f51a3e7e1df",
					"jsonFile" : "target-memcheck-Debug-cfd295200c0cbccadf00.json",
					"name" : "memcheck",
					"projectIndex" : 0
				},
				{
					"directoryIndex" : 0,
					"id" : "subgraph_search::@6890427a1f51a3e7e1df",
					"jsonFile" : "target-subgraph_search-Debug-287ca7d6b97ba183659d.json",
					"name" : "subgraph_search",
					"projectIndex" : 0
				},
				{
					"directoryIndex" : 0,
					"id" : "test::@6890427a1f51a3e7e1df",
					"jsonFile" : "target-test-Debug-07d6b2de658621742721.json",
					"name" : "test",
					"projectIndex" : 0
				},
				{
					"directoryIndex" : 0,
					"id" : "testFra::@6890427a1f51a3e7e1df",
					"jsonFile" : "target-testFra-Debug-06fb121d347fcea3661c.json",
					"name" : "testFra",
					"projectIndex" : 0
				}
			]
		}
	],
	"kind" : "codemodel",
	"paths" : 
	{
		"build" : "/home/dvillani/subgraph/MaxSubGraph_CUDA_C/build",
		"source" : "/home/dvillani/subgraph/MaxSubGraph_CUDA_C"
	},
	"version" : 
	{
		"major" : 2,
		"minor" : 6
	}
}
